Metadata-Version: 2.1
Name: aws-sso1
Version: 0.0.2241904
Summary: AWS SSO utility
Keywords: aws sso
Classifier: Programming Language :: Python :: 3
Classifier: License :: OSI Approved :: MIT License
Classifier: Operating System :: OS Independent
Requires-Python: >=3.11
Requires-Dist: beautifulsoup4~=4.9
Requires-Dist: boto3~=1.17
Requires-Dist: html5lib~=1.1
Requires-Dist: keyring~=23.0
Requires-Dist: requests~=2.25
Requires-Dist: requests-ntlm~=1.1
Requires-Dist: toml~=0.10
